LICENCE.txt
MANIFEST.in
README.rst
setup.py
cmsplugin_feedparser/__init__.py
cmsplugin_feedparser/cms_plugins.py
cmsplugin_feedparser/models.py
cmsplugin_feedparser/settings.py
cmsplugin_feedparser.egg-info/PKG-INFO
cmsplugin_feedparser.egg-info/SOURCES.txt
cmsplugin_feedparser.egg-info/dependency_links.txt
cmsplugin_feedparser.egg-info/not-zip-safe
cmsplugin_feedparser.egg-info/requires.txt
cmsplugin_feedparser.egg-info/top_level.txt
cmsplugin_feedparser/migrations/0001_initial.py
cmsplugin_feedparser/migrations/0002_update_related_name.py
cmsplugin_feedparser/migrations/__init__.py
cmsplugin_feedparser/south_migrations/0001_initial.py
cmsplugin_feedparser/south_migrations/__init__.py