Metadata-Version: 1.1
Name: cmsplugin-feedparser
Version: 0.3.0
Summary: 
